{
  "id": "PM0074-20",
  "priority": 70,
  "listing_type": "unit",
  "parent_id": "PM0074",
  "slugs": {
    "es": "unidad-20-orion-manilva",
    "en": "unit-20-orion-manilva",
    "de": "einheit-20-orion-manilva",
    "fr": "unite-20-orion-manilva",
    "it": "unita-20-orion-manilva",
    "nl": "unit-20-orion-manilva"
  },
  "status": "sold",
  "featured": false,
  "languages": [
    "es",
    "en",
    "de",
    "fr",
    "it",
    "nl"
  ],
  "transaction": "sale",
  "price": null,
  "currency": "EUR",
  "location": {
    "country": "ES",
    "province": "Malaga",
    "city": "Mijas",
    "area": "Las Lagunas",
    "coordinates": {
      "lat": 36.53577628175631,
      "lng": -4.639616603103012
    }
  },
  "property": {
    "type": "apartment",
    "market": "obra_nueva",
    "year_built": 2027,
    "area_m2": 82.75,
    "usable_area_m2": 47.51,
    "terrace_m2": 24.18,
    "garden_m2": null,
    "bedrooms": 1,
    "bathrooms": null,
    "garages": null,
    "floor_level": 1,
    "orientation": null,
    "condition": "new",
    "floor_label": "Planta 1",
    "type_label": "B",
    "useful_interior_m2": 35.42
  },
  "features": [
    "new_build",
    "terrace",
    "sea_views",
    "green_areas",
    "communal_pool",
    "gated_community"
  ],
  "media": {
    "cover": {
      "url": "https://gslfgcqwmcircqaslzij.supabase.co/storage/v1/object/public/properties/PM0074/cover/01_EXT_AEREA-v1.jpg",
      "alt": {
        "es": "Orion en Manilva - obra nueva",
        "en": "Orion in Manilva - new build",
        "de": "Orion in Manilva - Neubau",
        "fr": "Orion a Manilva - programme neuf",
        "it": "Orion a Manilva - nuova costruzione",
        "nl": "Orion in Manilva - nieuwbouw"
      }
    },
    "gallery": {
      "exterior": [
        {
          "url": "https://gslfgcqwmcircqaslzij.supabase.co/storage/v1/object/public/properties/PM0074/exterior/02_EXT_PERGOLA-v1.jpg"
        },
        {
          "url": "https://gslfgcqwmcircqaslzij.supabase.co/storage/v1/object/public/properties/PM0074/exterior/03_EXT_TERRAZAS--v1.jpg"
        },
        {
          "url": "https://gslfgcqwmcircqaslzij.supabase.co/storage/v1/object/public/properties/PM0074/exterior/04_EXT_PISCINA-v1.jpg"
        },
        {
          "url": "https://gslfgcqwmcircqaslzij.supabase.co/storage/v1/object/public/properties/PM0074/exterior/05_EXT_AGUA-v1.jpg"
        },
        {
          "url": "https://gslfgcqwmcircqaslzij.supabase.co/storage/v1/object/public/properties/PM0074/exterior/12_EXT_AEREA_NOCTURNA-v1.jpg"
        },
        {
          "url": "https://gslfgcqwmcircqaslzij.supabase.co/storage/v1/object/public/properties/PM0074/exterior/street-01.jpg"
        },
        {
          "url": "https://gslfgcqwmcircqaslzij.supabase.co/storage/v1/object/public/properties/PM0074/exterior/street-02.jpg"
        }
      ],
      "interior": [
        {
          "url": "https://gslfgcqwmcircqaslzij.supabase.co/storage/v1/object/public/properties/PM0074/interior/06_INT_SALON_sin-fondo-mar-v1.jpg"
        },
        {
          "url": "https://gslfgcqwmcircqaslzij.supabase.co/storage/v1/object/public/properties/PM0074/interior/07_INT_COCINA_sin-fondo-mar-v1.jpg"
        },
        {
          "url": "https://gslfgcqwmcircqaslzij.supabase.co/storage/v1/object/public/properties/PM0074/interior/08_TERRAZA_PISCINA_sin-fondo-mar-v1.jpg"
        },
        {
          "url": "https://gslfgcqwmcircqaslzij.supabase.co/storage/v1/object/public/properties/PM0074/interior/10_TERRAZA_FACHADA_sin-fondo-mar-v1.jpg"
        }
      ],
      "views": [
        {
          "url": "https://gslfgcqwmcircqaslzij.supabase.co/storage/v1/object/public/properties/PM0074/zonas-comunes/02_EXT_PERGOLA-v1.jpg"
        },
        {
          "url": "https://gslfgcqwmcircqaslzij.supabase.co/storage/v1/object/public/properties/PM0074/zonas-comunes/04_EXT_PISCINA-v1.jpg"
        }
      ],
      "floorplan": [
        {
          "url": "https://gslfgcqwmcircqaslzij.supabase.co/storage/v1/object/public/properties/PM0074/planos/2-1-B.pdf"
        }
      ]
    }
  },
  "seo": {
    "focus_keyphrase": {
      "es": "apartamento orion manilva unidad 20",
      "en": "orion manilva apartment unit 20",
      "de": "orion manilva apartment einheit 20",
      "fr": "appartement orion manilva unite 20",
      "it": "appartamento orion manilva unita 20",
      "nl": "orion manilva appartement unit 20"
    },
    "meta_description": {
      "es": "Unidad en Orion, Manilva. Consulte disponibilidad y detalles.",
      "en": "Unit at Orion, Manilva. Check availability and details.",
      "de": "Einheit in Orion, Manilva. Verfuegbarkeit und Details.",
      "fr": "Unite a Orion, Manilva. Consultez disponibilite et details.",
      "it": "Unita in Orion, Manilva. Verifica disponibilita e dettagli.",
      "nl": "Unit in Orion, Manilva. Bekijk beschikbaarheid en details."
    }
  },
  "translations": {
    "es": {
      "title": "Unidad 20 en Orion (Manilva)",
      "intro": "Unidad disponible en Orion con 1 dormitorios.",
      "description": []
    },
    "en": {
      "title": "Unit 20 at Orion (Manilva)",
      "intro": "Available unit in Orion with 1 bedrooms.",
      "description": []
    },
    "de": {
      "title": "Einheit 20 in Orion (Manilva)",
      "intro": "Verfuegbare Einheit in Orion mit 1 Schlafzimmern.",
      "description": []
    },
    "fr": {
      "title": "Unite 20 a Orion (Manilva)",
      "intro": "Unite disponible a Orion avec 1 chambres.",
      "description": []
    },
    "it": {
      "title": "Unita 20 a Orion (Manilva)",
      "intro": "Unita disponibile in Orion con 1 camere.",
      "description": []
    },
    "nl": {
      "title": "Unit 20 in Orion (Manilva)",
      "intro": "Beschikbare unit in Orion met 1 slaapkamers.",
      "description": []
    }
  }
}
